README.txt
setup.py
docs/HISTORY.txt
docs/INSTALL.txt
docs/LICENSE.GPL
docs/LICENSE.txt
wildcard/__init__.py
wildcard.uberoverride.egg-info/PKG-INFO
wildcard.uberoverride.egg-info/SOURCES.txt
wildcard.uberoverride.egg-info/dependency_links.txt
wildcard.uberoverride.egg-info/entry_points.txt
wildcard.uberoverride.egg-info/namespace_packages.txt
wildcard.uberoverride.egg-info/not-zip-safe
wildcard.uberoverride.egg-info/paster_plugins.txt
wildcard.uberoverride.egg-info/requires.txt
wildcard.uberoverride.egg-info/top_level.txt
wildcard/uberoverride/__init__.py
wildcard/uberoverride/configure.zcml
wildcard/uberoverride/tests.py
wildcard/uberoverride/tree-multi-widget.pt
wildcard/uberoverride/tree-select-widget.pt
wildcard/uberoverride/views.py
wildcard/uberoverride/widgets.py
wildcard/uberoverride/static/jqueryFileTree.css
wildcard/uberoverride/static/jqueryFileTree.js
wildcard/uberoverride/static/images/directory.png
wildcard/uberoverride/static/images/file.png
wildcard/uberoverride/static/images/folder_open.png
wildcard/uberoverride/static/images/spinner.gif