Metadata-Version: 1.0
Name: wildcard.uberoverride
Version: 1.0a1
Summary: UNKNOWN
Home-page: https://github.com/collective/wildcard.uberoverride
Author: Nathan Van Gheem
Author-email: vangheem@gmail.com
License: GPL
Keywords: widget selection tree uber
Platform: UNKNOWN
Classifier: Framework :: Plone
Classifier: Programming Language :: Python
Classifier: Framework :: Plone :: 4.0
Classifier: Framework :: Plone :: 4.1
Classifier: Framework :: Plone :: 4.2
Classifier: Framework :: Plone :: 4.3
